{
    "nodes": [
        {
            "name": "CS Common Room",
            "long": -122.9140499574846,
            "lat": 49.27721166258463,
            "edges": [
                {
                    "name": "ASB Entrance",
                    "cost": 1,
                    "isIndoor": true
                }
            ]
        },
        {
            "name": "ASB Entrance",
            "long": -122.91407547509968,
            "lat": 49.27769028134071,
            "edges": [
                {
                    "name": "CS Common Room",
                    "cost": 1,
                    "isIndoor": true
                },
                {
                    "name": "AQ SE",
                    "cost": 1.5,
                    "isIndoor": true
                },
                {
                    "name": "Transit Exchange",
                    "cost": 1.0,
                    "isIndoor": false
                },
                {
                    "name": "Parking East",
                    "cost": 1.0,
                    "isIndoor": false
                },
                {
                    "name": "Parking South",
                    "cost": 2.0,
                    "isIndoor": true
                },
                {
                    "name": "Nesters",
                    "cost": 0.9,
                    "isIndoor": false
                }
            ]
        },
        {
            "name": "AQ SE",
            "long": -122.915944640456,
            "lat": 49.27827918414656,
            "edges": [
                {
                    "name": "ASB Entrance",
                    "cost": 1.5,
                    "isIndoor": true
                },
                {
                    "name": "AQ SW",
                    "cost": 1,
                    "isIndoor": true
                },
                {
                    "name": "AQ NE",
                    "cost": 1,
                    "isIndoor": true
                },
                {
                    "name": "SSBB",
                    "cost": 0.5,
                    "isIndoor": true
                },
                {
                    "name": "SSBP",
                    "cost": 0.3,
                    "isIndoor": true
                }
            ]
        },
        {
            "name": "AQ NE",
            "long": -122.91555549682886,
            "lat": 49.279317550398964,
            "edges": [
                {
                    "name": "AQ SE",
                    "cost": 1,
                    "isIndoor": true
                },
                {
                    "name": "AQ NW",
                    "cost": 1,
                    "isIndoor": true
                },
                {
                    "name": "Saywell",
                    "cost": 0.5,
                    "isIndoor": true
                }
            ]
        },
        {
            "name": "AQ NW",
            "long": -122.91704461488418,
            "lat": 49.279572595548174,
            "edges": [
                {
                    "name": "AQ NE",
                    "cost": 1,
                    "isIndoor": true
                },
                {
                    "name": "AQ SW",
                    "cost": 1,
                    "isIndoor": true
                },
                {
                    "name": "SUB",
                    "cost": 1.5,
                    "isIndoor": false
                },
                {
                    "name": "RCB Images Theatre",
                    "cost": 0.25,
                    "isIndoor": true
                }
            ]
        },
        {
            "name": "AQ SW",
            "long": -122.9174688452362,
            "lat": 49.27852174923896,
            "edges": [
                {
                    "name": "AQ NW",
                    "cost": 1,
                    "isIndoor": true
                },
                {
                    "name": "AQ SE",
                    "cost": 1,
                    "isIndoor": true
                },
                {
                    "name": "SUB",
                    "cost": 1.0,
                    "isIndoor": true
                },
                {
                    "name": "SSBC",
                    "cost": 0.1,
                    "isIndoor": true
                },
                {
                    "name": "SSBB",
                    "cost": 0.5,
                    "isIndoor": true
                }
            ]
        },
        {
            "name": "SUB",
            "long": -122.918281,
            "lat": 49.278551,
            "edges": [
                {
                    "name": "AQ SW",
                    "cost": 1.0,
                    "isIndoor": true
                },
                {
                    "name": "AQ NW",
                    "cost": 1.5,
                    "isIndoor": false
                },
                {
                    "name": "MBC",
                    "cost": 0.5,
                    "isIndoor": true
                },
                {
                    "name": "Library",
                    "cost": 1.5,
                    "isIndoor": false
                }
            ]
        },
        {
            "name": "MBC",
            "long": -122.9193,
            "lat": 49.278761,
            "edges": [
                {
                    "name": "SUB",
                    "cost": 0.5,
                    "isIndoor": true
                },
                {
                    "name": "Library",
                    "cost": 1.0,
                    "isIndoor": false
                },
                {
                    "name": "Transportation Centre",
                    "cost": 1.0,
                    "isIndoor": false
                }
            ]
        },
        {
            "name": "Library",
            "long": -122.918742,
            "lat": 49.279601,
            "edges": [
                {
                    "name": "MBC",
                    "cost": 1.0,
                    "isIndoor": false
                },
                {
                    "name": "SUB",
                    "cost": 1.5,
                    "isIndoor": false
                },
                {
                    "name": "Transportation Centre",
                    "cost": 1.0,
                    "isIndoor": false
                },
                {
                    "name": "WMC East",
                    "cost": 1.5,
                    "isIndoor": false
                }
            ]
        },
        {
            "name": "Transportation Centre",
            "long": -122.920261,
            "lat": 49.279504,
            "edges": [
                {
                    "name": "Library",
                    "cost": 1.0,
                    "isIndoor": false
                },
                {
                    "name": "MBC",
                    "cost": 1.0,
                    "isIndoor": false
                },
                {
                    "name": "WMC East",
                    "cost": 1.0,
                    "isIndoor": false
                },
                {
                    "name": "LDC",
                    "cost": 1.5,
                    "isIndoor": false
                }
            ]
        },
        {
            "name": "WMC East",
            "long": -122.920846,
            "lat": 49.279875,
            "edges": [
                {
                    "name": "Transportation Centre",
                    "cost": 1.0,
                    "isIndoor": false
                },
                {
                    "name": "Library",
                    "cost": 1.5,
                    "isIndoor": false
                },
                {
                    "name": "WMC West",
                    "cost": 1.0,
                    "isIndoor": true
                },
                {
                    "name": "LDC",
                    "cost": 1.0,
                    "isIndoor": false
                }
            ]
        },
        {
            "name": "WMC West",
            "long": -122.922445,
            "lat": 49.28012,
            "edges": [
                {
                    "name": "WMC East",
                    "cost": 1.0,
                    "isIndoor": true
                },
                {
                    "name": "LDC",
                    "cost": 1.0,
                    "isIndoor": false
                },
                {
                    "name": "West Parking",
                    "cost": 0.5,
                    "isIndoor": false
                }
            ]
        },
        {
            "name": "LDC",
            "long": -122.922219,
            "lat": 49.279504,
            "edges": [
                {
                    "name": "WMC West",
                    "cost": 1.0,
                    "isIndoor": false
                },
                {
                    "name": "WMC East",
                    "cost": 1.0,
                    "isIndoor": false
                },
                {
                    "name": "Transportation Centre",
                    "cost": 1.5,
                    "isIndoor": false
                },
                {
                    "name": "Dining Hall",
                    "cost": 1.0,
                    "isIndoor": false
                }
            ]
        },
        {
            "name": "West Parking",
            "long": -122.923421,
            "lat": 49.280001,
            "edges": [
                {
                    "name": "WMC West",
                    "cost": 0.5,
                    "isIndoor": false
                },
                {
                    "name": "Dining Hall",
                    "cost": 1.0,
                    "isIndoor": false
                },
                {
                    "name": "Residence Courtyard",
                    "cost": 1.0,
                    "isIndoor": false
                },
                {
                    "name": "Residence Shell",
                    "cost": 0.5,
                    "isIndoor": false
                }
            ]
        },
        {
            "name": "Dining Hall",
            "long": -122.924408,
            "lat": 49.27991,
            "edges": [
                {
                    "name": "West Parking",
                    "cost": 1.0,
                    "isIndoor": false
                },
                {
                    "name": "LDC",
                    "cost": 1.0,
                    "isIndoor": false
                },
                {
                    "name": "Residence Towers",
                    "cost": 1.0,
                    "isIndoor": false
                },
                {
                    "name": "Residence Courtyard",
                    "cost": 1.0,
                    "isIndoor": false
                },
                {
                    "name": "Residence Shell",
                    "cost": 0.5,
                    "isIndoor": false
                },
                {
                    "name": "Residence McTaggart-Cowan",
                    "cost": 0.5,
                    "isIndoor": false
                }
            ]
        },
        {
            "name": "SSBC",
            "long": -122.917606,
            "lat": 49.278329,
            "edges": [
                {
                    "name": "AQ SW",
                    "cost": 0.1,
                    "isIndoor": true
                }
            ]
        },
        {
            "name": "SSBB",
            "long": -122.91678,
            "lat": 49.278248,
            "edges": [
                {
                    "name": "AQ SW",
                    "cost": 0.5,
                    "isIndoor": true
                },
                {
                    "name": "AQ SE",
                    "cost": 0.5,
                    "isIndoor": true
                }
            ]
        },
        {
            "name": "SSBP",
            "long": -122.916061,
            "lat": 49.27794,
            "edges": [
                {
                    "name": "AQ SE",
                    "cost": 0.3,
                    "isIndoor": true
                }
            ]
        },
        {
            "name": "Saywell",
            "long": -122.914728,
            "lat": 49.279389,
            "edges": [
                {
                    "name": "AQ NE",
                    "cost": 0.5,
                    "isIndoor": true
                },
                {
                    "name": "Blusson",
                    "cost": 1.0,
                    "isIndoor": true
                },
                {
                    "name": "Parking North",
                    "cost": 1.0,
                    "isIndoor": false
                }
            ]
        },
        {
            "name": "Blusson",
            "long": -122.913006,
            "lat": 49.279091,
            "edges": [
                {
                    "name": "Saywell",
                    "cost": 1.0,
                    "isIndoor": true
                },
                {
                    "name": "Parking North",
                    "cost": 1.0,
                    "isIndoor": false
                },
                {
                    "name": "Transit Exchange",
                    "cost": 0.5,
                    "isIndoor": false
                }
            ]
        },
        {
            "name": "RCB Images Theatre",
            "long": -122.916851,
            "lat": 49.279733,
            "edges": [
                {
                    "name": "AQ NW",
                    "cost": 0.25,
                    "isIndoor": true
                }
            ]
        },
        {
            "name": "Residence Towers",
            "long": -122.926758,
            "lat": 49.280047,
            "edges": [
                {
                    "name": "Dining Hall",
                    "cost": 1.0,
                    "isIndoor": false
                },
                {
                    "name": "Residence Townhouses",
                    "cost": 1.0,
                    "isIndoor": false
                },
                {
                    "name": "Parking Residence West",
                    "cost": 1.0,
                    "isIndoor": false
                }
            ]
        },
        {
            "name": "Residence Townhouses",
            "long": -122.929689,
            "lat": 49.280065,
            "edges": [
                {
                    "name": "Residence Towers",
                    "cost": 1.0,
                    "isIndoor": false
                },
                {
                    "name": "Parking Residence West",
                    "cost": 1.0,
                    "isIndoor": false
                }
            ]
        },
        {
            "name": "Residence Courtyard",
            "long": -122.923534,
            "lat": 49.280336,
            "edges": [
                {
                    "name": "Dining Hall",
                    "cost": 1.0,
                    "isIndoor": false
                },
                {
                    "name": "West Parking",
                    "cost": 1.0,
                    "isIndoor": false
                }
            ]
        },
        {
            "name": "Residence Shell",
            "long": -122.923947,
            "lat": 49.279367,
            "edges": [
                {
                    "name": "Dining Hall",
                    "cost": 0.5,
                    "isIndoor": false
                },
                {
                    "name": "West Parking",
                    "cost": 0.5,
                    "isIndoor": false
                },
                {
                    "name": "Residence McTaggart-Cowan",
                    "cost": 0.5,
                    "isIndoor": false
                }
            ]
        },
        {
            "name": "Residence McTaggart-Cowan",
            "long": -122.925489,
            "lat": 49.279172,
            "edges": [
                {
                    "name": "Residence Shell",
                    "cost": 0.5,
                    "isIndoor": false
                },
                {
                    "name": "Dining Hall",
                    "cost": 0.5,
                    "isIndoor": false
                }
            ]
        },
        {
            "name": "Parking Residence West",
            "long": -122.929062,
            "lat": 49.278433,
            "edges": [
                {
                    "name": "Residence Townhouses",
                    "cost": 1.0,
                    "isIndoor": false
                },
                {
                    "name": "Residence Towers",
                    "cost": 1.0,
                    "isIndoor": false
                },
                {
                    "name": "Residence McTaggert-Cowan",
                    "cost": 1.5,
                    "isIndoor": false
                }
            ]
        },
        {
            "name": "Parking North",
            "long": -122.912974,
            "lat": 49.28005,
            "edges": [
                {
                    "name": "Blusson",
                    "cost": 1.0,
                    "isIndoor": false
                },
                {
                    "name": "Saywell",
                    "cost": 1.0,
                    "isIndoor": false
                }
            ]
        },
        {
            "name": "Transit Exchange",
            "long": -122.912743,
            "lat": 49.278587,
            "edges": [
                {
                    "name": "Blusson",
                    "cost": 0.5,
                    "isIndoor": false
                },
                {
                    "name": "ASB Entrance",
                    "cost": 1.0,
                    "isIndoor": false
                },
                {
                    "name": "North Parking",
                    "cost": 0.75,
                    "isIndoor": false
                },
                {
                    "name": "Parking East",
                    "cost": 1.0,
                    "isIndoor": true
                },
                {
                    "name": "Nesters",
                    "cost": 1.0,
                    "isIndoor": false
                }
            ]
        },
        {
            "name": "Parking East",
            "long": -122.911236,
            "lat": 49.277027,
            "edges": [
                {
                    "name": "ASB Entrance",
                    "cost": 1.0,
                    "isIndoor": false
                },
                {
                    "name": "Transit Exchange",
                    "cost": 1.0,
                    "isIndoor": true
                },
                {
                    "name": "Parking South",
                    "cost": 1.0,
                    "isIndoor": false
                }
            ]
        },
        {
            "name": "Parking South",
            "long": -122.912394,
            "lat": 49.275201,
            "edges": [
                {
                    "name": "Parking East",
                    "cost": 1.0,
                    "isIndoor": false
                },
                {
                    "name": "ASB Entrance",
                    "cost": 2.0,
                    "isIndoor": true
                }
            ]
        },
        {
            "name": "Nesters",
            "long": -122.910267,
            "lat": 49.277876,
            "edges": [
                {
                    "name": "Transit Exchange",
                    "cost": 1.0,
                    "isIndoor": false
                },
                {
                    "name": "ASB Entrance",
                    "cost": 0.9,
                    "isIndoor": false
                }
            ]
        }
    ]
}